sbsgenerator-1.0.5.dist-info/METADATA
sbsgenerator-1.0.5.dist-info/WHEEL
sbsgenerator-1.0.5.dist-info/license_files/LICENSE
sbsgenerator/logging.py
sbsgenerator/__init__.py
sbsgenerator/generator.py
sbsgenerator/download.py
sbsgenerator/sbsgenerator.pypy310-pp73-aarch64-linux-gnu.so
sbsgenerator-1.0.5.dist-info/RECORD
