Metadata-Version: 2.3
Name: sbsgenerator
Version: 1.0.5
Classifier: Development Status :: 5 - Production/Stable
Classifier: Intended Audience :: Science/Research
Classifier: License :: OSI Approved :: MIT License
Classifier: Operating System :: MacOS
Classifier: Operating System :: Microsoft :: Windows
Classifier: Operating System :: POSIX :: Linux
Classifier: Programming Language :: Python :: 3
Classifier: Programming Language :: Python :: 3.8
Classifier: Programming Language :: Python :: 3.9
Classifier: Programming Language :: Python :: 3.10
Classifier: Programming Language :: Python :: 3.11
Classifier: Programming Language :: Python :: 3.12
Classifier: Programming Language :: Python :: 3.13
Classifier: Programming Language :: Python :: Implementation :: CPython
Classifier: Programming Language :: Python
Classifier: Programming Language :: Rust
Requires-Dist: numpy ==1.23.1
Requires-Dist: requests ==2.31.0
Requires-Dist: dask ==2024.1.1
Requires-Dist: pandas ==1.5.0
Requires-Dist: pytest ; extra == 'test'
Requires-Dist: ruff ; extra == 'dev'
Requires-Dist: version ; extra == 'dynamic'
Provides-Extra: test
Provides-Extra: dev
Provides-Extra: dynamic
License-File: LICENSE
Summary: Blazingly fast SBS matrix generator library
Keywords: sbs,matrix,sbsgenerator,Single Base Substitution,bioinformatics,genomics,genetics,biology,sequence,sequence analysis
Author-email: Jan Alfonso Busker <alfonsobusker@gmail.com>
Requires-Python: >=3.8
Project-URL: Homepage, https://github.com/AlfonsoJan/sbsgenerator
Project-URL: Changelog, https://github.com/AlfonsoJan/sbsgenerator/blob/main/CHANGES.md
